fastapi_login_shield/__init__.py
fastapi_login_shield/middleware.py
fastapi_login_shield-0.1.9.dist-info/METADATA
fastapi_login_shield-0.1.9.dist-info/WHEEL
fastapi_login_shield-0.1.9.dist-info/RECORD
