Metadata-Version: 2.4
Name: fastapi-login-shield
Version: 0.1.9
Summary: Protect FastAPI login endpoints from brute-force attacks using middleware
Project-URL: Homepage, https://mrmrprogrammer.ir
Project-URL: Documentation, https://github.com/MrMrProgrammer/fastapi-login-shield#readme
Project-URL: Repository, https://github.com/MrMrProgrammer/fastapi-login-shield
Project-URL: Issues, https://github.com/MrMrProgrammer/fastapi-login-shield/issues
Author-email: Seyed Mohammadreza Hashemi <mrmrprogrammer@gmail.com>
Maintainer-email: MrMrProgrammer <mrmrprogrammer@gmail.com>
License: MIT
Keywords: brute-force,fastapi,login-protection,middleware,rate-limiter,security
Classifier: Development Status :: 3 - Alpha
Classifier: Framework :: FastAPI
Classifier: License :: OSI Approved :: MIT License
Classifier: Operating System :: OS Independent
Classifier: Programming Language :: Python :: 3
Classifier: Topic :: Internet :: WWW/HTTP :: HTTP Servers
Classifier: Topic :: Security
Requires-Python: >=3.7
Requires-Dist: fastapi>=0.95.0
Requires-Dist: starlette>=0.27.0
